hatch_polylith_bricks/polylith/building/__init__.py
hatch_polylith_bricks/polylith/building/core.py
hatch_polylith_bricks/polylith/building/paths.py
hatch_polylith_bricks/polylith/hatch/__init__.py
hatch_polylith_bricks/polylith/hatch/core.py
hatch_polylith_bricks/polylith/hatch/hooks/__init__.py
hatch_polylith_bricks/polylith/hatch/hooks/bricks.py
hatch_polylith_bricks/polylith/hatch_hooks/__init__.py
hatch_polylith_bricks/polylith/hatch_hooks/hooks.py
hatch_polylith_bricks/polylith/parsing/__init__.py
hatch_polylith_bricks/polylith/parsing/core.py
hatch_polylith_bricks/polylith/parsing/rewrite.py
hatch_polylith_bricks/polylith/repo/__init__.py
hatch_polylith_bricks/polylith/repo/get.py
hatch_polylith_bricks/polylith/repo/repo.py
hatch_polylith_bricks/polylith/toml/__init__.py
hatch_polylith_bricks/polylith/toml/core.py
hatch_polylith_bricks-1.5.2.dist-info/METADATA
hatch_polylith_bricks-1.5.2.dist-info/WHEEL
hatch_polylith_bricks-1.5.2.dist-info/entry_points.txt
hatch_polylith_bricks-1.5.2.dist-info/RECORD
