Metadata-Version: 2.3
Name: hatch-polylith-bricks
Version: 1.5.2
Summary: Hatch build hook plugin for Polylith
License: MIT
Author: David Vujic
Requires-Python: >=3.8,<4.0
Classifier: Framework :: Hatch
Classifier: License :: OSI Approved :: MIT License
Classifier: Programming Language :: Python :: 3
Classifier: Programming Language :: Python :: 3.8
Classifier: Programming Language :: Python :: 3.9
Classifier: Programming Language :: Python :: 3.10
Classifier: Programming Language :: Python :: 3.11
Classifier: Programming Language :: Python :: 3.12
Classifier: Programming Language :: Python :: 3.13
Requires-Dist: hatchling (>=1.21.0,<2.0.0)
Requires-Dist: tomlkit (==0.*)
Project-URL: Homepage, https://davidvujic.github.io/python-polylith-docs/
Project-URL: Repository, https://github.com/davidvujic/python-polylith
